{
"mo7wwqi3j4twkn45rkyxpnak":["aetherain","Uncle Mlynar"],
"peucmu7xgnx6nr7tlm4ugka7":["evik","Evik Mlynářů"],
"2tou4owmq3m5ruwmp2ije6ur":["jjmlynarek","Julia Mlynarek (She/Her/Elle)"],
"2hnnth43npfiqodp6ewqi5o2":["mlyon0486","Michael "],
"4s3fwyvn6psbteofoo465vdw":["mlynxqualey","M Lynx Qualey"],
"hq77kp4y5riwckc2ztp3e7jk":["mlynchik","Мале крольча"],
"n27pw7bbyk2lcapdazimiypf":["mlyp","Howl’s Moving Castle Doctrine"],
"pyqfunkjbvyoyoxm6pmkpa6o":["mlygoncalves","Mly"],
"swlejzfsajgq7hlezznmtnxn":["mlyntc","M'lyn"],
"uwg6wj5lsfppp6q2ghaptkb3":["mly","Bambi, o furão "],
"olsasfdkquhnmurnq6p22jj4":["mlynx3000","Three Gator Mike "],
"bumt6k3zwsvajhkb43mvojnu":["mlyt","MT"],
"tohjplju77comdlia2sl66sq":["mlynch","Mike"],
"r7sanfu4x5dkduv3kbr2vyfi":["mlyn","Andrew Beskorovayny "],
"unbwoafa4lppm4jydjxu6exh":"mly1221",
"7yszjzyb23at34cu55m46ckt":["mlyeko","enoki 🍄🌱"],
"ehnc32ez42m6jzlfrmlorl7f":["mlyavyi","Принцес Ірлуан "],
"5zh34m4tonnsdaazfopkixsm":"mlyzhng",
"nzcyswfhitbjd534p6fgzzwj":"mlynds",
"itms5lct7phppxsgzm7qibtm":["mlymly000","Mly"],
"ce3spdslnufjxhocsf6lewzp":["mlyman","M Lyman"],
"jjvaf7spfu3bl2az4svkfopd":"mlybollinger",
"2552g3esmxwawdwpvcq4c6ss":["mlyki","Max"],
"iffhro2qzcqpn44tmgcte6xg":["mlynarka","Mlynářka"],
"5ebtxblet6cacaqkpoc3w7qo":["mlynd","Lyn"],
"5ol3pqxzcftzgpyspgex3bai":["mlyntsitosvyate","Mattie"],
"hle23fgl22dotr5wypbr7czu":["mlynneauthor","M. Lynne Squires, Author "],
"ehe3wn4aoxoohh4vnx3e2sjs":["woodedwoods","Kamila Mlynarczyk Woodedwoods"]
}
