{
"6jlujngu36y4sxjfge3e3btp":["mxonica","moni ☭"],
"o4jyylsdpveb7nuowmknfwqr":["mxoberon","Shomari Kirkwood"],
"hs4bc6oc3pn2xx4gjltuvooe":["mxowl","white is the color of death"],
"6e5dhxorp5sodzafmmghrcow":"mxolisi",
"epaqpm4vte4tw6rhq5bx5xmo":["mxowlex","MxOwlex"],
"o5zbkirbfmq6ctioe2trzbip":["mxorange","Chiffon"],
"lqpduru6cxrqpvmrn7sdn45u":["mxozempicub","Ste"],
"h7n2lk42zxta6l5exxvz7ihu":["mxo1on","(っ˘ڡ˘ς) @MXO1ON@everywhere"],
"jabq7mwkt6lodeclvp2jrklt":"mxoxy",
"6bb45wsjxonvdqismjme4x3j":["teammxo","Mxo"]
}
