{
"oczyxvbq667jkowehv2odbd3":["mrssakurahatake","MSH"],
"dagusawdw4rsvf2u3nuk76gq":["mshak","Mshak to you"],
"itq56t46edmil5nno3bhk77q":["mshaller","Ms Haller | HE"],
"kdpt4qobajdqrdlhzutodped":["mshcrowder","Hannah Crowder"],
"kstgtyh7t4ylevjukauaxxam":["msh1486","Mahdi"],
"oxi2tx4u27wawdrbbmbpqoo6":["msheatherbeaver","Ms 🦫"],
"stb256efziua2qt457o24e3w":["mshcherbatskaya","Answers to \"Mish\""],
"yazte7dv6ghz45smzfe4joru":["mshooper","Ms Hooper"],
"yfwssa4uamiv57m34qitshxh":["msheathcliff","Danielle"],
"z4fulazlknt2hzelc2soxibv":["msheartstrings","Laura 👩🏼‍💻 storyteller 🦄 autumn girl 🍁🎃"],
"sevgwev2gbd5ihz2xbu3f7sx":["mshk","Masahiko Tachizono"],
"wheau6g65vjewhicjmzg45f3":["mshamma","Mohammad Shamma"],
"ggjvp6xmufjp2suhbntvb5qp":"msh",
"dfp462elhombzbtupby5npus":"mshao",
"tqzbkdhf5t643extumta2ejy":"mshishan",
"lmnzypgmdnqadldm5akk4qpp":["mshartistry","Midday 🍀💎"],
"gpsukzorxs2xlksu7npoeka7":"mshariatmadar",
"322vjfxcactnyn2jkvnw2jg4":["mshagerdi","Mehran"],
"f4zi3qrfdl2ota37jmxq7egf":["mshannahmurphy","Hannah Murphy"],
"lhsu7btjtycotvphvsgjaci7":["mshelton","Martin"],
"pnuncgzfs56snavordhxc6xh":"mshah",
"rw24glqij63dzokhh6etvpuz":"msherrard",
"v7bvdclxjr64ywaavd5vhng3":"mshobeiri",
"jbf24jbiwysxykq5s5yhascl":["mshades01","Chris Gladis "],
"bjglmdippbu6dl3beujg6qmd":["mshouji","庄司昌彦/ Masahiko SHOJI"],
"4bvu6nxkfdbuolb4oztuhzst":["mshell","Miles"],
"tcgik2byyuddm4xftor7kv2t":["mshahawy","Mohamed Shahawy"],
"sn57gpse3fcmmxt3uwwrlghn":["mshahamirian","Mehdi Shahamirian "],
"g3dosssfraum3iys4cm44a7y":"mshrohta",
"xjyap3gys4zkhm7slt4yzuej":["mshirvan","Mozhgun Ghafari Shirvan"],
"beki2cpmoyuc3bys3vpxlgiw":["mshomali","Mehran"],
"gapbregi4bxgyol7zosg6oph":["mshiryan","محسن شیریان "],
"tsvzgbfkx4xvw27vuxxvhp5k":["mshokoohi","Mehdi Shokoohi "],
"qjfoi4qebniygplnt5ksm4mt":["mshoney","Mel"],
"h2qi7iqsseiboooc6dxdqg7z":["mshm1991","مُنا 🌻🍒"],
"bmi3s7ao3vr6b2snjiygdxr7":"msharifpourmd",
"45cqie3jsks2536h5xdjuwar":["mshatchetface","Lucretia Hatchetface "],
"gwfwl66yi5hffaggr5u2c5le":"mshal",
"gerrc252pjtltrl7bqxt5o7c":["mshokouhmand","M.shokouhmand"],
"7hbkqirnzvv2xw7st7i2qla5":"mshavilayh",
"6wyuiaa45at2lzsquohl3e2u":"msharif",
"dciduywgeahl4hldtlw2nsw6":"mshanahan",
"3pssnhn76lds3twqpjrizctj":["mshdpotatoes","Mshd Potatoes"],
"g3t2pumrrnteckpia2hqqrib":["mshr-h.com","mshr-h"],
"gh23fe4rkvwq3p7j7ndqpjrl":["mshel","Mshel"],
"eths72zp3n4bnkqknilahqke":"mshattiecrane",
"whmlfts4wfuhahcie6ni2qfp":["mshadmehri","Mostafa shadmehri"],
"uos5t4dm7zqaybh4i2zr4ink":["mshah1025","Mehul Shah"],
"m4lzwmok7sqzue7v6l3oavua":"mshahin",
"keedov4qqvbtxr5ntqmon3fe":"mshbee",
"d6ytug2xnu2jhbfxwsjoc7vy":"mshiran",
"cown3jxjfky62rwasjct7lbl":"msharifi",
"pf2ks4gpkhaz72bvm6vtecnq":"mshnd",
"ncwzvvi22mqocoagf5xu7i6n":["mshellenberger","Michael Shellenberger"],
"alj6zdoxdcgh5edringtx4aw":["mshepherd","Matt Shepherd"],
"k3i526nwerxg2lu4i6tkozlv":["mshwery","Matt Shwery"],
"eppged7p5n4zw4uyutjptbqy":"mshoteu",
"lfj2bip45zhyzt5iwl6ln6ez":["mshawahneh","Mohammad Shawahneh "],
"hinx32lrpodbikfqg4z2erka":["mshew9","Michael Shew"],
"ksglci5qn5wml432ott3twzy":["msheridan","m"],
"yhboxgqzfjwktpgmw7ox3ptk":"msherretz",
"pf7wvo7sahsdr5ssytnpcdm3":"mshaw",
"z2ch4ygrtgt4xvvkheqk3iyw":["msholliday93","Ameerah Holliday"],
"3jbi3f5xdlxp2uogeuiag7h2":"mshaffer",
"5s22jslhkus3hvpgpeblesc5":["mshea","Meghan M. Shea"],
"pvjijgbl2b22ck2r2otihpsu":["mshafsaqureshi","Hafsa Qureshi"],
"exkqb42fflsatuilncnjzep6":["msheensource","Michael Sheen Source"],
"5s5ueshsh6ctfq3inyf2magx":["mshvan","MVH"],
"6cvgqhgrutsfc3zsex4jjb2h":"mshiffrin",
"tjalpdgf6rjeqqkng7yy56er":["mshopoff","Michael Shopoff"],
"dlc4z6qhlywck74hzm3y4ufp":"mshick",
"elfmql2grkdjrjqm2foxlg6w":["mshurricane","Like The Hurricane "],
"vzxi5huqpgb43vkigappoks4":"mshadmehri21",
"cbmyiudvzfp7qk3bowxmnjqq":"msh73",
"gkjk6hj4niy7mvrfo6m23txb":"msh10",
"eojvh6hn775kk4qjfpvmrxwd":["mshots","der wannabre"],
"e7rdrzcwldrig2rdv2gvp72w":"mshahoyi",
"jmk3xxr42o4tb5en7w5hj6sm":"mshmb",
"ydaufs56kvywehwecbrum6jh":["mshavishamburglar","Ms. Havishamburlgar"],
"fhe3jv7eudxu5exj3lfejtcn":"mshazer",
"y6wot6smovv3anr7zsbwketp":"mshj",
"oneqzzm4nnu5zgslc7ljz3kt":"mshelley",
"62jdtrlmcofsmalvdtyhwf5y":"mshenefelt",
"6nvi2jf5o5gb7bbmcthjxugc":"mshoilman",
"yujxjah3vwyysyciny2hqb3r":["mshoneyb40","MsHoneyB"],
"7jowims4mp2sap4i2atdj524":"mshanks",
"2pt43imqukakfgv3uqfg5mdc":["mshasegawa","Michael Hasegawa"],
"wtc57swoe4h3szxsjoz4hoqx":["mshr554","pu"],
"xcpztzwrs4n72c7txoxemcpm":["mshakir","Sᴀнᴇʙ⁩"],
"s2biff77fyhmtlqyip4xjclw":["mshaler","Michael Shaler"],
"fi7dasyaajisvoc6bk6swqnj":"msherwood",
"cwewntfuqyyn3yvcw2enjkai":["mshibata","しばたまさあき"],
"r45cmbam3k4y5yzuwyon4cvx":"mshub",
"gtzrnjw2cagrhileut6ztcpd":["mshasha","하샤/젠"],
"tushcxpu3ecibwtxicwx5n5h":["mshotter","Michael Shotter"],
"jgz5u5d3lwbs2t6m3wrwv6kr":["mshenandoah","めっっしゅ"],
"rjn4ny2m2naff2ssn2oiy6dq":"mshilarygail",
"jvoo7skx6dwoimndwstzc5k7":["mshko","msh // kai-ou"],
"p4z5hqjtkecbosuzxzkjmkep":["mshgxxs","🇺🇦маша-гусíчка в метамодерні ★⁵ "],
"htojhoqjiyd6yu2pjq3mndhh":["mshks","masa"],
"6goowsi2utapx7tzvxglkvs4":["mshioxxx","🐇"],
"x4i5ynzgandeaaffagsmjlgo":["mshipstory","Lindsay Adams"],
"7i2ykijsslvgurk7akckotdj":["mshbond","Miss Hayley Bond"],
"ibixibg6a6vm5wejnk7gkvcr":"mshibuya",
"lkyy6leflydd7wnsx5g6bhf7":["mshelicat","Helen Miller"],
"b6ni5crzaujc5cuuloibzwiq":["mshayleydavis","Mshayleydavis "],
"6gdux5mtaoize46427hj2wcs":["mshurtubise","Nicole Hurtubise"],
"anxkkloaktgyeu7nriqrplik":["mshatter","Melanie S. Hatter "],
"sxea62awavrqzs26y3ctq4nu":["mshahn","Michael Hahn"],
"weimzditgjwcvnkemlbkkfio":"msheadshot",
"v7r4khtbjallskg437jk7uiq":["mshoboslayer","mshoboslayer"],
"omujjwbydc7x3ubkhl7popvw":["mshwaikh","Malaka Shwaikh"],
"k4qzcoq7ivkobmy5czqiux7a":["mshanetutwiler","M. Shane Tutwiler"],
"hanmfqp6yiaswi43nob76wzq":["mshelenhanna","Helen Hanna"],
"hlsi5ltmr7tmxraqk7kvdn34":"mshipleysky",
"yafhnlmnvrmj7e5qt4rerlrw":["mshagina","Dr Maria Shagina"],
"7zszrmraxohuvy4gxugchfsi":"mshelfer",
"6xul5zwtquab4ihbpwdw3kqm":["mshireman","Mark"],
"iuoirzietf6ihobeznaytqpg":["mshu","M. Saïd H. Unger"],
"s32g3fqgqpkqnytneqoh7nl7":"msheatherwebb",
"ijbfmyz5rpca5677ns2l64v3":"msholidayjones",
"rkjpgoqrzstinsivtutvgq4t":"mshalsimon",
"wn2o6z5ztpv5fpvro7qe3w3h":"mshughes",
"kocvikno7vdjawcg4tzsxsi6":["mshadowy","MShadowy"],
"cmjpxygtdaj5anxu6ycepsa7":["mshelenjay","Helen Jeffery"],
"2dkupmjxlw6jrbsv36iki2fs":["mshoh","MsHoh"],
"zjuly7jlaxsuomzwqssvmmqw":"mshaql4d",
"5qrplxhkkqyrk5saclukdt5i":["mshdk","Martin Schultz"],
"kzn4eucpyad4l5vwvirc5rcj":"mshaw85",
"6oll35nwwbvyswqs5f2tjjil":["msharaf","M. Sharaf"],
"qhfgljj2glyrz6pfwibqtfq5":["mshighhighheels","Google is free "],
"xi2tbp7jydbffojda2udqqa3":"mshafer",
"cyqbvtxi5umfbsq5m44mfieb":"mshari",
"ws3c2vntpvmsqkols25pp6o7":"msha",
"d4a2myklwsrxstc6r5nsu3qg":"mshelenblake",
"5u7xs6n377gyinlt42ak7uvw":["mshm","Marija Sh"],
"i4np7vlfl7oefzgb4uxt4omp":"mshc26",
"qirg4dsdaxdqzfb7g7g4wwlv":["mshixxx","眞白"],
"rfoehqmmvsqcq3hvz6psc74h":["mshoude","Mélodie Simard-Houde"],
"vah6awffcnjrmtwma2utv4n4":["mshantil","Hanna Tillmanns"],
"fwu4uroufmbiwgcs24nyeumy":["mshort2928","Matt Short"],
"wp52cskbqh3zqvhghemovftm":["mshoji","Moe"],
"x2pygx3jgm5fdsipbvinrjax":["newsjunkie","MSH"],
"bxwel2jbbrntrhxxbipv5zjr":["s10tgstn","mshi"],
"vlu7phn7ukzdmfdklid6av5q":["thanhneville","Thanh Neville, MD, MSHS"],
"qf6cpxs6p2via7m2yfekyk7w":["tn2mshows","TN2M Shows"],
"bcpnxnalpiopaqfxdw2kn5y5":["tzym","TzyMshm"]
}
