{
"xxifgs5i2hur3lhjqis5jt7k":["jayisdumb","MSJay"],
"d2p3dogetrs7x2subdfj5ur2":["msjoycetarot","Ms. Joyce Tarot"],
"eavvoexzjdclzij6mjtfzuzw":["msjoanne","Joanne"],
"j3a762gtes2jdm4f2kd27gfr":["msjennimiller","jenni miller "],
"kee3j5ypmdn4nfp6m3kcl3oc":["msjg","MsJG "],
"oj5blc3orcaoahohplfbaoz2":["msjnba","Morten Stig Jensen"],
"qk4xau3rqgbwq6brgi4o3fla":["msjs2021","JS"],
"r5dp7bsmzz2mkoj7udktgvio":["msjdan","MsJDan"],
"tj4p2xb2fvg76h32irl3u6nf":["msjadis","Mistress Jadis Ives "],
"vzlajyyukdbo2uqpsgfu56vz":"msjanice",
"wzzw6q6ep3ocuyt4zutlhudg":["msjayteer","Jay Rattray"],
"pg3e2asr4gf3icnbuhg7jpko":["msjess","MsJess"],
"cahc2rky4am66lw3i446cmve":["msjavan","Morteza"],
"sp34t3qxiiwbrft4c7jycfeo":["msjen","Ms. Jen"],
"yc3jf2itkbmun432vlbafh7k":["msjamshidi","Maryam Jamshidi "],
"ihk5bun5jiopvy3drjzrcfur":["msjune","Ms. June"],
"iodwvbvd2sw7gip76yop4lvt":["msjoknows","MsJoKnows.eth"],
"ecxk37bkigfswsfg5aweafxk":"msjgriffiths",
"veqt45vey64xc75utti7hprb":["msjuliefowler","Ms Julie Fowler BA MA FCIM"],
"szok6ucqex6rkoucf5jzfhcd":["msj","Michael Simon Johnson"],
"wdue3pzkmou4oeqluolwbqhf":["msjadehelm15","Miss Jade Helm ‘15"],
"hnt3ml4fm23m3ohlhhgwjxxa":"msjinxie",
"w7ypj2uogg7ronx77pjnvnbh":["msjacke","Jackeline"],
"ocqdn3z4i5cjg2k36tebiqwt":["msjulia","Julia"],
"ytqn5qqrmhk5ily7spzgimzy":["msjaneeyrehead","Jane Eyrehead"],
"7auwwvcd7vmultsesbxjgxwk":["msjatahy","bereca"],
"u2tz7nhppyk74ys45g26vgt4":["msjkh","Jill"],
"xtaoit2ireoaka2h3o7x2wus":["msjulz","Juliet Orjiogo"],
"ou5zn6i2se7v2oegyimotalb":"msjendi",
"jvqqjdybu4kjew6h2ujt2gv4":["msjenix","Jennifer E Nix"],
"vvyvrntzu6xn6ignpyck3jap":["msjolly","Jojo (Jolly)"],
"l5s5bpzjsnlzcv7e6iswn5dm":["msjunebuggie","Juniper Maxine 🏳️‍⚧️"],
"mmnn7r5y6ouob7qmyi6xwjsa":["msjoeybug","Joey Paul📚🖋🏳️‍🌈👩‍🦽"],
"rodeeaghvrfgmgdkr4n22rnt":["msjay","MsJay"],
"gjsf4osfotd3b2oqehmvljhu":"msjerome",
"oxxjgvwagsssl24hxbwzehne":["msjenniferg","Jennifer Griffin"],
"axxaid6izy56kgl2wez3hljc":["msjenjwalker","Ms Jen J Walker"],
"3xdh4vg3khqqhnjnr2v6ycve":["msjwolf","ʲ"],
"ytmxlrn2gmsqdnjb2bmvmz2m":"msjessi.ca",
"hrxa7kcdyggijkzmujmerjao":"msjemmxswift",
"r7dat5cuidk5h3teknyc5kfe":["msjenkitch","Jen"],
"uey6f6jjw6umd7grmbhhiarg":["msjennifer","Ms Jennifer"],
"evzqhpgnhtzkqx53gwqneugc":["msjunojadec","Juno Jade"],
"nkbi2o2zawr6mjtktsvth6oq":"msjasminestone",
"qopuejtx7h7nw7zg6cnr2dnd":"msjiminy",
"be4xl7zcqemj2xgatk2jwk5b":["msjenchan","💖MsJen 💖"],
"uowr3smfu3eir3xt3ke3fofz":"msjinx",
"y6o3hnuobtqj5wf4afjsjp2l":["msjeanrhys","Jean Rhys"],
"bmrl5x3eol2re6xspdutj6tx":["msjanssen","Msjanssen"],
"73f3fs6dzwn4bqqdo3u7lpyp":["msjaneymac","Jane McCarthy"],
"fee2li5gxc2tcuiw3ingzde4":["msjostrom","Mattias Sjöström"],
"5cqdlk55fpbcgn3ytv47tjs5":["msjv","Mikko Välttilä"],
"kvutzainfjjau7pwde55qn2z":["msjojo","Jojo"],
"hat6xvhmumjhxryanf7t7atu":"msjazmyn",
"z3qdej6zcuhb26j6z4jsbbxp":["msjasminemn","Jasmine Lane"],
"hfu7aapagr2ue37cftnah7oq":"msjoblom",
"3ss6mnl2y6jzbw55s4vhg6un":"msjewellmarceau",
"ji35mhy5rxhug6yvdsksxceq":["msjacobs","Ms. Jacobs Worries About Democracy"],
"7yi4fmwrazwdk37rbhw6amp6":["wxandpi","MSJ | Spotter | Student "]
}
